xylo/__init__.py
xylo/cli.py
xylo/config.py
xylo/templates/cookiecutter.json
xylo/templates/{{cookiecutter.name}}/.ignore
xylo/templates/{{cookiecutter.name}}/.xylo/backend/__init__.py
xylo/templates/{{cookiecutter.name}}/.xylo/backend/server.py
xylo/templates/{{cookiecutter.name}}/.xylo/frontend/.eslintrc.json
xylo/templates/{{cookiecutter.name}}/.xylo/frontend/.gitignore
xylo/templates/{{cookiecutter.name}}/.xylo/frontend/README.md
xylo/templates/{{cookiecutter.name}}/.xylo/frontend/app/favicon.ico
xylo/templates/{{cookiecutter.name}}/.xylo/frontend/app/globals.css
xylo/templates/{{cookiecutter.name}}/.xylo/frontend/app/layout.tsx
xylo/templates/{{cookiecutter.name}}/.xylo/frontend/next.config.mjs
xylo/templates/{{cookiecutter.name}}/.xylo/frontend/package-lock.json
xylo/templates/{{cookiecutter.name}}/.xylo/frontend/package.json
xylo/templates/{{cookiecutter.name}}/.xylo/frontend/postcss.config.mjs
xylo/templates/{{cookiecutter.name}}/.xylo/frontend/public/next.svg
xylo/templates/{{cookiecutter.name}}/.xylo/frontend/public/vercel.svg
xylo/templates/{{cookiecutter.name}}/.xylo/frontend/tailwind.config.ts
xylo/templates/{{cookiecutter.name}}/.xylo/frontend/tsconfig.json
xylo/templates/{{cookiecutter.name}}/xylo/backend/pyproject.toml
xylo/templates/{{cookiecutter.name}}/xylo/backend/src/{{cookiecutter.name_with_underscores}}_backend/__init__.py
xylo/templates/{{cookiecutter.name}}/xylo/backend/src/{{cookiecutter.name_with_underscores}}_backend/info.py
xylo/templates/{{cookiecutter.name}}/xylo/frontend/.gitignore
xylo/templates/{{cookiecutter.name}}/xylo/frontend/package-lock.json
xylo/templates/{{cookiecutter.name}}/xylo/frontend/package.json
xylo/templates/{{cookiecutter.name}}/xylo/frontend/rollup.config.mjs
xylo/templates/{{cookiecutter.name}}/xylo/frontend/src/index.tsx
xylo/templates/{{cookiecutter.name}}/xylo/frontend/tsconfig.json
xylo/templates/{{cookiecutter.name}}/xylo.yaml
xylo-0.4.0.dist-info/METADATA
xylo-0.4.0.dist-info/WHEEL
xylo-0.4.0.dist-info/entry_points.txt
xylo-0.4.0.dist-info/RECORD
