Metadata-Version: 2.1
Name: xylo
Version: 0.4.0
Summary: App framework
Author: Steve G
Author-email: steve@pagekey.io
Requires-Python: >=3.8,<4.0
Classifier: Programming Language :: Python :: 3
Classifier: Programming Language :: Python :: 3.8
Classifier: Programming Language :: Python :: 3.9
Classifier: Programming Language :: Python :: 3.10
Classifier: Programming Language :: Python :: 3.11
Classifier: Programming Language :: Python :: 3.12
Requires-Dist: click (>=8.1.7,<9.0.0)
Requires-Dist: cookiecutter (>=2.6.0,<3.0.0)
Requires-Dist: flask (>=3.0.3,<4.0.0)
Requires-Dist: flask-cors (>=5.0.0,<6.0.0)
Requires-Dist: pydantic (>=2.9.1,<3.0.0)
Requires-Dist: pyyaml (>=6.0.2,<7.0.0)
